{
  "metatypes": {
    "a": {
      "supportedMetatypes": ["Dwarf", "Ork", "Troll"],
      "adjustmentPoints": 13
    },
    "b": {
      "supportedMetatypes": ["Dwarf", "Elf", "Ork", "Troll"],
      "adjustmentPoints": 11
    },
    "c": {
      "supportedMetatypes": ["Dwarf", "Elf", "Human", "Ork", "Troll"],
      "adjustmentPoints": 9
    },
    "d": {
      "supportedMetatypes": ["Dwarf", "Elf", "Human", "Ork", "Troll"],
      "adjustmentPoints": 4
    },
    "e": {
      "supportedMetatypes": ["Dwarf", "Elf", "Human", "Ork", "Troll"],
      "adjustmentPoints": 1
    }
  },
  "attributes": {
    "a": 24,
    "b": 16,
    "c": 12,
    "d": 8,
    "e": 2
  },
  "skills": {
    "a": 32,
    "b": 24,
    "c": 20,
    "d": 16,
    "e": 10
  },
  "mag/res": {
    "a": {
      "Full": ["Magic", 4],
      "Aspected": ["Magic", 5],
      "Mystic Adept": ["Magic", 4],
      "Adept": ["Magic", 4],
      "Technomancer": ["Resonance", 4]
    },
    "b": {
      "Full": ["Magic", 3],
      "Aspected": ["Magic", 4],
      "Mystic Adept": ["Magic", 3],
      "Adept": ["Magic", 3],
      "Technomancer": ["Resonance", 3]
    },
    "c": {
      "Full": ["Magic", 2],
      "Aspected": ["Magic", 3],
      "Mystic Adept": ["Magic", 2],
      "Adept": ["Magic", 2],
      "Technomancer": ["Resonance", 2]
    },
    "d": {
      "Full": ["Magic", 1],
      "Aspected": ["Magic", 2],
      "Mystic Adept": ["Magic", 1],
      "Adept": ["Magic", 1],
      "Technomancer": ["Resonance", 1]
    },
    "e": {
      "Mundane": []
    }
  },
  "resources": {
    "a": 450000,
    "b": 275000,
    "c": 150000,
    "d": 50000,
    "e": 8000
  }
}
